SysOps/__init__.py
SysOps/main.py
kvx_sysops-1.1.1.dist-info/licenses/LICENSE.txt
kvx_sysops-1.1.1.dist-info/METADATA
kvx_sysops-1.1.1.dist-info/WHEEL
kvx_sysops-1.1.1.dist-info/entry_points.txt
kvx_sysops-1.1.1.dist-info/top_level.txt
kvx_sysops-1.1.1.dist-info/RECORD
